expstats/__init__.py
expstats/api.py
expstats/py.typed
expstats/business/__init__.py
expstats/business/guardrails.py
expstats/business/impact.py
expstats/diagnostics/__init__.py
expstats/diagnostics/health.py
expstats/diagnostics/novelty.py
expstats/diagnostics/srm.py
expstats/effects/__init__.py
expstats/effects/outcome/__init__.py
expstats/effects/outcome/base.py
expstats/effects/outcome/conversion.py
expstats/effects/outcome/magnitude.py
expstats/effects/outcome/timing.py
expstats/methods/__init__.py
expstats/methods/bayesian.py
expstats/methods/sequential.py
expstats/planning/__init__.py
expstats/planning/duration.py
expstats/planning/mde.py
expstats/segments/__init__.py
expstats/segments/analysis.py
expstats/utils/__init__.py
expstats/utils/math.py
expstats/utils/stats.py
expstats/utils/validation.py
expstats-0.2.0.dist-info/licenses/LICENSE
expstats-0.2.0.dist-info/METADATA
expstats-0.2.0.dist-info/WHEEL
expstats-0.2.0.dist-info/entry_points.txt
expstats-0.2.0.dist-info/top_level.txt
expstats-0.2.0.dist-info/RECORD
