Metadata-Version: 2.4
Name: expstats
Version: 0.2.0
Summary: Statistical tools for A/B testing - sample size calculation, power analysis, significance testing, Bayesian analysis, sequential testing, and business impact projections
Author: expstats contributors
License: MIT
Project-URL: Homepage, https://github.com/expstats/expstats
Project-URL: Documentation, https://github.com/expstats/expstats#readme
Project-URL: Repository, https://github.com/expstats/expstats
Project-URL: Issues, https://github.com/expstats/expstats/issues
Keywords: ab-testing,statistics,sample-size,power-analysis,hypothesis-testing,experimentation
Classifier: Development Status :: 4 - Beta
Classifier: Intended Audience :: Developers
Classifier: Intended Audience :: Science/Research
Classifier: License :: OSI Approved :: MIT License
Classifier: Operating System :: OS Independent
Classifier: Programming Language :: Python :: 3
Classifier: Programming Language :: Python :: 3.9
Classifier: Programming Language :: Python :: 3.10
Classifier: Programming Language :: Python :: 3.11
Classifier: Programming Language :: Python :: 3.12
Classifier: Topic :: Scientific/Engineering :: Mathematics
Classifier: Topic :: Software Development :: Libraries :: Python Modules
Requires-Python: >=3.9
License-File: LICENSE
Requires-Dist: numpy>=1.21.0
Requires-Dist: scipy>=1.7.0
Requires-Dist: pydantic>=2.0.0
Requires-Dist: fastapi>=0.100.0
Requires-Dist: uvicorn>=0.20.0
Provides-Extra: dev
Requires-Dist: pytest>=7.0.0; extra == "dev"
Requires-Dist: pytest-cov>=4.0.0; extra == "dev"
Requires-Dist: black>=23.0.0; extra == "dev"
Requires-Dist: ruff>=0.1.0; extra == "dev"
Requires-Dist: mypy>=1.0.0; extra == "dev"
Dynamic: license-file
